src/rtl/main_memory.sv
module main_memory #(
    parameter MEMORY_HEX   = "",
    parameter MEMORY_BYTES = 1024
) (
    input clk,

    // region control by [STAGE 1 FETCH]
    // Instruction Memory
    input      [ADDR_WIDTH-1:0] instr_addr,  // instruction memory address
    output reg [          31:0] instr,       // instruction from memory
    input                       instr_stb,   // request for instruction
    output reg                  instr_ack,   // ack
    // endregion control by [STAGE 1 FETCH]

    // region control by [STAGE 4 MEMORY]
    // Data Memory
    input                       wb_cyc,
    input                       wb_stb,
    input                       wb_wr_en,
    input      [ADDR_WIDTH-1:0] wb_addr,
    input      [          31:0] wb_wr_data,
    input      [           3:0] wb_wr_sel,
    output reg                  wb_ack,
    output                      wb_stall,
    output reg [          31:0] wb_rd_data
    // endregion control by [STAGE 4 MEMORY]
);
  localparam ADDR_WIDTH = $clog2(MEMORY_BYTES);
  localparam MEMORY_DEPTH = MEMORY_BYTES / 4;
  reg [31:0] memory[0:MEMORY_DEPTH-1];

  assign wb_stall = 0;  // never stall

  initial begin
    instr_ack <= 0;
    wb_ack    <= 0;
    instr     <= 0;
    if (MEMORY_HEX != "") begin
      $readmemh(MEMORY_HEX, memory);
      $display("Init Memory from %s", MEMORY_HEX);
    end else $display("No Memory Init");
  end

  always @(posedge clk) begin : sync_read_process
    instr_ack  <= instr_stb;  // ack go high next cycle after receiving stb (request)
    instr      <= memory[instr_addr>>2];  // read instruction

    wb_ack     <= (wb_stb && wb_cyc);  // ack go high next cycle after receiving stb (request)
    wb_rd_data <= memory[wb_addr[ADDR_WIDTH-1:2]];  // read data
  end

  always @(posedge clk) begin : sync_write_process
    if (wb_wr_en && wb_stb && wb_cyc) begin
      if (wb_wr_sel[0]) memory[wb_addr[ADDR_WIDTH-1:2]][7:0] <= wb_wr_data[7:0];
      if (wb_wr_sel[1]) memory[wb_addr[ADDR_WIDTH-1:2]][15:8] <= wb_wr_data[15:8];
      if (wb_wr_sel[2]) memory[wb_addr[ADDR_WIDTH-1:2]][23:16] <= wb_wr_data[23:16];
      if (wb_wr_sel[3]) memory[wb_addr[ADDR_WIDTH-1:2]][31:24] <= wb_wr_data[31:24];
    end
  end

endmodule

src/rtl/fetch.sv
module fetch #(
    parameter PC_RESET = 0
) (
    input clk,
    input rst,

    // region control Main Memory's Instruction Memory
    // Instruction Memory
    output reg [31:0] main_memory_instr_addr,  // instruction memory address
    input      [31:0] main_memory_instr,       // instruction from memory
    output            main_memory_instr_req,   // request for instruction
    input             main_memory_instr_ack,   // ack
    // endregion control Main Memory's Instruction Memory

    output reg [31:0] fetch_instr,  // fetched instruction sent to pipeline

    // region PC control
    output reg [31:0] pc,  // PC value of current instruction

    // control from [STAGE 5 WRITEBACK]
    input        writeback_change_pc,  // high when pc needs to change (trap/return from trap)
    input [31:0] writeback_next_pc,    // next PC due to trap

    // control from [STAGE 3 EXECUTE]
    input        execute_change_pc,  // high when pc needs to change (branch/jump)
    input [31:0] execute_next_pc,    // next PC due to branch/jump
    // endregion PC control


    // region Pipeline control
    input      stall,       // stall this stage
    input      flush,       // flush this stage
    output reg next_clk_en  // output clk enable for pipeline stalling of next state
    // endregion Pipeline control
);

  reg r_clk_en;
  reg r_clk_en_d;
  reg r_stall;

  /* Stall conditions
  stall this stage when:
  - stall this stage
  - memory instruction requested but no ack yet
  - no memory instruction request at all (no instruction to execute for this stage)
  */
  wire stall_bit = (  // stall conditions check bit
  stall ||  // stall this stage
  (main_memory_instr_req && (!main_memory_instr_ack)) || // memory instruction requested but no ack yet
  (!main_memory_instr_req) // no memory instruction request at all (no instruction to execute for this stage)
  );

  assign main_memory_instr_req = r_clk_en;  // request for new instruction if this stage is enabled

  // region clk enable logic for [STAGE 1 FETCH]
  // need to change pc ? (change pc signals from [STAGE 3 EXECUTE] or [STAGE 5 WRITEBACK])
  wire change_pc = (execute_change_pc || writeback_change_pc);

  // disable next stage if need to change pc not stall
  wire disable_next_stage = (change_pc && !(stall));

  always @(posedge clk, posedge rst) begin
    if (rst) r_clk_en <= 0;
    // do pipeline bubble when need to change pc so that the next stage will be disable
    // and will not execute the instruction already inside the pipeline
    else
      r_clk_en <= (!disable_next_stage);
  end
  // endregion clk enable logic for [STAGE 1 FETCH]

  // region update internal registers
  reg [31:0] prev_pc;
  reg [31:0] stalled_instr;
  reg [31:0] stalled_pc;

  /* Update registers conditions:
  - this stage is not stalled and currently enabled
  - this stage is stalled and currently enable but the next stage is disabled.
  - writeback change pc
  */
  wire enable_update_registers = (  //
  ((!stall) && r_clk_en) ||  // this stage is not stalled and currently enabled
  (stall && r_clk_en && (!next_clk_en))|| // this stage is stalled and currently enable but the next stage is disabled.
  writeback_change_pc  // writeback change pc
  );

  always @(posedge clk, posedge rst) begin
    if (rst) begin
      next_clk_en            <= 0;
      main_memory_instr_addr <= PC_RESET;
      prev_pc                <= PC_RESET;
      stalled_instr          <= 0;
      pc                     <= 0;
      fetch_instr            <= 0;
      r_stall                <= 0;
      stalled_pc             <= 0;
    end else begin
      // update registers
      if (enable_update_registers) begin
        main_memory_instr_addr <= r_main_memory_instr_addr;
        pc                     <= r_stall ? stalled_pc : main_memory_instr;
        fetch_instr            <= r_stall ? stalled_instr : main_memory_instr;
      end
      // flush next stage (only when not stalled) so that clock-enable of next stage is disabled at next clock cycle
      if ((!stall_bit) && flush) next_clk_en <= 0;
      // next stage enable only when not stalled
      else if (!stall_bit) next_clk_en <= r_clk_en_d;
      // if this stage is not forced to be stalled but still be stall from other conditions (mem ack, no mem req), disable next stage (make a pipeline bubble)
      else if (stall_bit && (!stall)) next_clk_en <= 0;

      // raise stall when any of 5 stages is stalled
      r_stall <= stall;

      // store pc and instr before stalling the stage so we can come back to the prev values when we need to return from stall
      if (stall_bit && (!r_stall)) begin
        stalled_pc <= prev_pc;
        stalled_instr <= main_memory_instr;
      end

      // first delay to align PC to the pipeline
      prev_pc <= main_memory_instr_addr;
    end
  end
  // endregion update internal registers

  // region pc and pipeline clk enable control logic
  reg [31:0] r_main_memory_instr_addr;

  always_comb begin
    r_main_memory_instr_addr = 0;
    r_clk_en_d               = 0;
    if (writeback_change_pc) begin
      r_main_memory_instr_addr = writeback_next_pc;
      r_clk_en_d               = 0;
    end else if (execute_change_pc) begin
      r_main_memory_instr_addr = execute_next_pc;
      r_clk_en_d               = 0;
    end else begin
      r_main_memory_instr_addr = main_memory_instr + 4;
      r_clk_en_d               = r_clk_en;
    end
  end
  // endregion pc and pipeline clk enable control logic

endmodule

src/tb/fetch_tb.sv
`timescale 1ns / 1ps
`define VCD_FILE "./vcds/fetch_tb.vcd"

module fetch_tb ();


  localparam PC_RESET = 'h1000;

  parameter MEMORY_HEX = "./hexs/add.hex";
  parameter MEMORY_BYTES = 1024;
  localparam ADDR_WIDTH = $clog2(MEMORY_BYTES);
  localparam MEMORY_DEPTH = MEMORY_BYTES / 4;

  initial begin
    $dumpfile(`VCD_FILE);
    $dumpvars;
  end

  parameter CLK_PERIOD = 10;  // 100 MHz clk
  parameter CLK_PERIOD_HALF = CLK_PERIOD / 2;
  parameter CLK_PERIOD_QUAR = CLK_PERIOD / 4;
  always #(CLK_PERIOD_HALF) clk = !clk;

  initial begin
    clk                 <= 0;
    rst                 <= 0;
    writeback_change_pc <= 0;
    writeback_next_pc   <= 0;
    execute_change_pc   <= 0;
    execute_next_pc     <= 0;
    stall               <= 0;
    flush               <= 0;
  end

  initial begin
    reset(10);
    #(CLK_PERIOD * 10);
    reset(10);
    #(CLK_PERIOD * 10);
    $finish;
  end

  task automatic instruction_fetch;
    begin

    end
  endtask  //automatic

  task automatic reset;
    input integer clk_period;
    begin
      rst <= 1;
      repeat (clk_period) #(CLK_PERIOD);
      rst <= 0;
    end
  endtask  //automatic

  reg         clk;
  reg         rst;

  wire [31:0] main_memory_instr_addr;
  wire [31:0] main_memory_instr;
  wire        main_memory_instr_req;
  wire        main_memory_instr_ack;

  wire [31:0] fetch_instr;

  wire [31:0] pc;

  reg         writeback_change_pc;
  reg  [31:0] writeback_next_pc;

  reg         execute_change_pc;
  reg  [31:0] execute_next_pc;

  reg         stall;
  reg         flush;
  wire        next_clk_en;


  fetch #(
      .PC_RESET(PC_RESET)
  ) fetch_inst (
      .clk(clk),
      .rst(rst),

      .main_memory_instr_addr(main_memory_instr_addr),
      .main_memory_instr     (main_memory_instr),
      .main_memory_instr_req (main_memory_instr_req),
      .main_memory_instr_ack (main_memory_instr_ack),

      .fetch_instr(fetch_instr),

      .pc(pc),

      .writeback_change_pc(writeback_change_pc),
      .writeback_next_pc  (writeback_next_pc),

      .execute_change_pc(execute_change_pc),
      .execute_next_pc  (execute_next_pc),

      .stall      (stall),
      .flush      (flush),
      .next_clk_en(next_clk_en)
  );


  reg         wb_cyc = 0;
  reg         wb_stb = 0;
  reg         wb_wr_en = 0;
  reg  [31:0] wb_addr = 0;
  reg  [31:0] wb_wr_data = 0;
  reg  [ 3:0] wb_wr_sel = 0;
  wire        wb_ack;
  wire        wb_stall;
  wire [31:0] wb_rd_data;

  main_memory #(
      .MEMORY_HEX  (MEMORY_HEX),
      .MEMORY_BYTES(MEMORY_BYTES)
  ) main_memory_inst (
      .clk(clk),

      .instr_addr(main_memory_instr_addr),
      .instr     (main_memory_instr),
      .instr_stb (main_memory_instr_req),
      .instr_ack (main_memory_instr_ack),

      .wb_cyc    (wb_cyc),
      .wb_stb    (wb_stb),
      .wb_wr_en  (wb_wr_en),
      .wb_addr   (wb_addr),
      .wb_wr_data(wb_wr_data),
      .wb_wr_sel (wb_wr_sel),
      .wb_ack    (wb_ack),
      .wb_stall  (wb_stall),
      .wb_rd_data(wb_rd_data)
  );
endmodule

vcds/fetch_tb.vcd
$date
	Wed Jun 26 16:56:49 2024
$end
$version
	Icarus Verilog
$end
$timescale
	1ps
$end
$scope module fetch_tb $end
$var wire 1 ! wb_stall $end
$var wire 32 " wb_rd_data [31:0] $end
$var wire 1 # wb_ack $end
$var wire 32 $ pc [31:0] $end
$var wire 1 % next_clk_en $end
$var wire 1 & main_memory_instr_req $end
$var wire 32 ' main_memory_instr_addr [31:0] $end
$var wire 1 ( main_memory_instr_ack $end
$var wire 32 ) main_memory_instr [31:0] $end
$var wire 32 * fetch_instr [31:0] $end
$var parameter 32 + ADDR_WIDTH $end
$var parameter 32 , CLK_PERIOD $end
$var parameter 32 - CLK_PERIOD_HALF $end
$var parameter 32 . CLK_PERIOD_QUAR $end
$var parameter 32 / MEMORY_BYTES $end
$var parameter 32 0 MEMORY_DEPTH $end
$var parameter 112 1 MEMORY_HEX $end
$var parameter 32 2 PC_RESET $end
$var reg 1 3 clk $end
$var reg 1 4 execute_change_pc $end
$var reg 32 5 execute_next_pc [31:0] $end
$var reg 1 6 flush $end
$var reg 1 7 rst $end
$var reg 1 8 stall $end
$var reg 32 9 wb_addr [31:0] $end
$var reg 1 : wb_cyc $end
$var reg 1 ; wb_stb $end
$var reg 32 < wb_wr_data [31:0] $end
$var reg 1 = wb_wr_en $end
$var reg 4 > wb_wr_sel [3:0] $end
$var reg 1 ? writeback_change_pc $end
$var reg 32 @ writeback_next_pc [31:0] $end
$scope module fetch_inst $end
$var wire 1 A change_pc $end
$var wire 1 3 clk $end
$var wire 1 B disable_next_stage $end
$var wire 1 C enable_update_registers $end
$var wire 1 4 execute_change_pc $end
$var wire 32 D execute_next_pc [31:0] $end
$var wire 1 6 flush $end
$var wire 1 & main_memory_instr_req $end
$var wire 1 7 rst $end
$var wire 1 8 stall $end
$var wire 1 E stall_bit $end
$var wire 1 ? writeback_change_pc $end
$var wire 32 F writeback_next_pc [31:0] $end
$var wire 1 ( main_memory_instr_ack $end
$var wire 32 G main_memory_instr [31:0] $end
$var parameter 32 H PC_RESET $end
$var reg 32 I fetch_instr [31:0] $end
$var reg 32 J main_memory_instr_addr [31:0] $end
$var reg 1 % next_clk_en $end
$var reg 32 K pc [31:0] $end
$var reg 32 L prev_pc [31:0] $end
$var reg 1 M r_clk_en $end
$var reg 1 N r_clk_en_d $end
$var reg 32 O r_main_memory_instr_addr [31:0] $end
$var reg 1 P r_stall $end
$var reg 32 Q stalled_instr [31:0] $end
$var reg 32 R stalled_pc [31:0] $end
$upscope $end
$scope module main_memory_inst $end
$var wire 1 3 clk $end
$var wire 10 S instr_addr [9:0] $end
$var wire 1 & instr_stb $end
$var wire 10 T wb_addr [9:0] $end
$var wire 1 : wb_cyc $end
$var wire 1 ! wb_stall $end
$var wire 1 ; wb_stb $end
$var wire 32 U wb_wr_data [31:0] $end
$var wire 1 = wb_wr_en $end
$var wire 4 V wb_wr_sel [3:0] $end
$var parameter 32 W ADDR_WIDTH $end
$var parameter 32 X MEMORY_BYTES $end
$var parameter 32 Y MEMORY_DEPTH $end
$var parameter 112 Z MEMORY_HEX $end
$var reg 32 [ instr [31:0] $end
$var reg 1 ( instr_ack $end
$var reg 1 # wb_ack $end
$var reg 32 \ wb_rd_data [31:0] $end
$scope begin sync_read_process $end
$upscope $end
$scope begin sync_write_process $end
$upscope $end
$upscope $end
$scope task instruction_fetch $end
$upscope $end
$scope task reset $end
$upscope $end
$upscope $end
$enddefinitions $end
$comment Show the parameter values. $end
$dumpall
b10111000101111011010000110010101111000011100110010111101100001011001000110010000101110011010000110010101111000 Z
b100000000 Y
b10000000000 X
b1010 W
b1000000000000 H
b1000000000000 2
b10111000101111011010000110010101111000011100110010111101100001011001000110010000101110011010000110010101111000 1
b100000000 0
b10000000000 /
b10 .
b101 -
b1010 ,
b1010 +
$end
#0
$dumpvars
bx \
b0 [
b0 V
b0 U
b0 T
b0 S
b0 R
b0 Q
0P
b100 O
0N
0M
b1000000000000 L
b0 K
b1000000000000 J
b0 I
b0 G
b0 F
1E
b0 D
0C
0B
0A
b0 @
0?
b0 >
0=
b0 <
0;
0:
b0 9
08
17
06
b0 5
04
03
b0 *
b0 )
0(
b1000000000000 '
0&
0%
b0 $
0#
bx "
0!
$end
#5000
b110010000000000000010010111 O
b110010000000000000010010011 "
b110010000000000000010010011 \
b110010000000000000010010011 )
b110010000000000000010010011 G
b110010000000000000010010011 [
13
#10000
03
#15000
13
#20000
03
#25000
13
#30000
03
#35000
13
#40000
03
#45000
13
#50000
03
#55000
13
#60000
03
#65000
13
#70000
03
#75000
13
#80000
03
#85000
13
#90000
03
#95000
13
#100000
07
03
#105000
1C
1N
b110010000000000000010010111 O
1E
b110010000000000000010010011 Q
b1000000000000 R
1&
1M
13
#110000
03
#115000
0E
b10010111 S
b110010000000000000010010011 *
b110010000000000000010010011 I
b110010000000000000010010011 $
b110010000000000000010010011 K
b110010000000000000010010111 '
b110010000000000000010010111 J
1(
13
#120000
03
#125000
1N
b110011011101100111001000001001 O
b110010000000000000010010111 L
1%
b110011011101100111001000000101 )
b110011011101100111001000000101 G
b110011011101100111001000000101 [
13
#130000
03
#135000
b1000001001 S
b110011011101100111001000000101 *
b110011011101100111001000000101 I
b110011011101100111001000000101 $
b110011011101100111001000000101 K
b110011011101100111001000001001 '
b110011011101100111001000001001 J
13
#140000
03
#145000
1N
b100 O
b110011011101100111001000001001 L
b0 )
b0 G
b0 [
13
#150000
03
#155000
b100 S
b0 *
b0 I
b0 $
b0 K
b100 '
b100 J
13
#160000
03
#165000
1N
b1001011000000000000100010111 O
b100 L
b1001011000000000000100010011 )
b1001011000000000000100010011 G
b1001011000000000000100010011 [
13
#170000
03
#175000
b100010111 S
b1001011000000000000100010011 *
b1001011000000000000100010011 I
b1001011000000000000100010011 $
b1001011000000000000100010011 K
b1001011000000000000100010111 '
b1001011000000000000100010111 J
13
#180000
03
#185000
1N
b100 O
b1001011000000000000100010111 L
b0 )
b0 G
b0 [
13
#190000
03
#195000
b100 S
b0 *
b0 I
b0 $
b0 K
b100 '
b100 J
13
#200000
0C
b0 S
0N
b100 O
1E
b0 R
b0 Q
b1000000000000 L
b1000000000000 '
b1000000000000 J
0%
0&
0M
17
03
#205000
b110010000000000000010010111 O
b110010000000000000010010011 )
b110010000000000000010010011 G
b110010000000000000010010011 [
0(
13
#210000
03
#215000
13
#220000
03
#225000
13
#230000
03
#235000
13
#240000
03
#245000
13
#250000
03
#255000
13
#260000
03
#265000
13
#270000
03
#275000
13
#280000
03
#285000
13
#290000
03
#295000
13
#300000
07
03
#305000
1C
1N
b110010000000000000010010111 O
1E
1&
1M
b110010000000000000010010011 Q
b1000000000000 R
13
#310000
03
#315000
0E
b10010111 S
b110010000000000000010010011 *
b110010000000000000010010011 I
b110010000000000000010010011 $
b110010000000000000010010011 K
b110010000000000000010010111 '
b110010000000000000010010111 J
1(
13
#320000
03
#325000
1N
b110011011101100111001000001001 O
b110010000000000000010010111 L
1%
b110011011101100111001000000101 )
b110011011101100111001000000101 G
b110011011101100111001000000101 [
13
#330000
03
#335000
b1000001001 S
b110011011101100111001000000101 *
b110011011101100111001000000101 I
b110011011101100111001000000101 $
b110011011101100111001000000101 K
b110011011101100111001000001001 '
b110011011101100111001000001001 J
13
#340000
03
#345000
1N
b100 O
b110011011101100111001000001001 L
b0 )
b0 G
b0 [
13
#350000
03
#355000
b100 S
b0 *
b0 I
b0 $
b0 K
b100 '
b100 J
13
#360000
03
#365000
1N
b1001011000000000000100010111 O
b100 L
b1001011000000000000100010011 )
b1001011000000000000100010011 G
b1001011000000000000100010011 [
13
#370000
03
#375000
b100010111 S
b1001011000000000000100010011 *
b1001011000000000000100010011 I
b1001011000000000000100010011 $
b1001011000000000000100010011 K
b1001011000000000000100010111 '
b1001011000000000000100010111 J
13
#380000
03
#385000
1N
b100 O
b1001011000000000000100010111 L
b0 )
b0 G
b0 [
13
#390000
03
#395000
b100 S
b0 *
b0 I
b0 $
b0 K
b100 '
b100 J
13
