src/rtl/main_memory.sv
module main_memory #(
    parameter MEMORY_HEX   = "",
    parameter MEMORY_BYTES = 1024
) (
    input clk,

    // region control by [STAGE 1 FETCH]
    // Instruction Memory
    input      [ADDR_WIDTH-1:0] instr_addr,  // instruction memory address
    output reg [          31:0] instr,       // instruction from memory
    input                       instr_stb,   // request for instruction
    output reg                  instr_ack,   // ack
    // endregion control by [STAGE 1 FETCH]

    // region control by [STAGE 4 MEMORY]
    // Data Memory
    input                       wb_cyc,
    input                       wb_stb,
    input                       wb_wr_en,
    input      [ADDR_WIDTH-1:0] wb_addr,
    input      [          31:0] wb_wr_data,
    input      [           3:0] wb_wr_sel,
    output reg                  wb_ack,
    output                      wb_stall,
    output reg [          31:0] wb_rd_data
    // endregion control by [STAGE 4 MEMORY]
);
  localparam ADDR_WIDTH = $clog2(MEMORY_BYTES);
  localparam MEMORY_DEPTH = MEMORY_BYTES / 4;
  reg [31:0] memory[0:MEMORY_DEPTH-1];

  assign wb_stall = 0;  // never stall

  initial begin
    instr_ack <= 0;
    wb_ack    <= 0;
    instr     <= 0;
    if (MEMORY_HEX != "") begin
      $readmemh(MEMORY_HEX, memory);
      $display("Init Memory from %s", MEMORY_HEX);
    end else $display("No Memory Init");
  end

  always @(posedge clk) begin : sync_read_process
    instr_ack  <= instr_stb;  // ack go high next cycle after receiving stb (request)
    instr      <= memory[instr_addr>>2];  // read instruction

    wb_ack     <= (wb_stb && wb_cyc);  // ack go high next cycle after receiving stb (request)
    wb_rd_data <= memory[wb_addr[ADDR_WIDTH-1:2]];  // read data
  end

  always @(posedge clk) begin : sync_write_process
    if (wb_wr_en && wb_stb && wb_cyc) begin
      if (wb_wr_sel[0]) memory[wb_addr[ADDR_WIDTH-1:2]][7:0] <= wb_wr_data[7:0];
      if (wb_wr_sel[1]) memory[wb_addr[ADDR_WIDTH-1:2]][15:8] <= wb_wr_data[15:8];
      if (wb_wr_sel[2]) memory[wb_addr[ADDR_WIDTH-1:2]][23:16] <= wb_wr_data[23:16];
      if (wb_wr_sel[3]) memory[wb_addr[ADDR_WIDTH-1:2]][31:24] <= wb_wr_data[31:24];
    end
  end

endmodule

src/tb/main_memory_tb.sv
`timescale 1ns / 1ps
`define VCD_FILE "./vcds/main_memory_tb.vcd"

module main_memory_tb ();
  parameter MEMORY_HEX = "./hexs/add.hex";
  parameter MEMORY_BYTES = 1024;
  localparam ADDR_WIDTH = $clog2(MEMORY_BYTES);
  localparam MEMORY_DEPTH = MEMORY_BYTES / 4;

  initial begin
    $dumpfile(`VCD_FILE);
    $dumpvars;
  end

  initial begin
    clk = 0;
    instr_addr = 0;
    instr_stb = 0;
    wb_cyc = 0;
    wb_stb = 0;
    wb_wr_en = 0;
    wb_addr = 0;
    wb_wr_data = 0;
    wb_wr_sel = 0;
  end

  task automatic instruction_read;
    input [31:0] read_from_address;
    output match;
    begin
      @(negedge clk);
      instr_stb  <= 1;
      instr_addr <= read_from_address;
      @(posedge clk);
      #(CLK_PERIOD_QUAR);
      match = (instr == hex_file_data[read_from_address[ADDR_WIDTH-1:2]]);
      $display(  //
          "[%s] Read Instruction %h from address %h, expected %h",  //
          (match) ? "  OK  " : "FAILED",  //
          instr,  //
          instr_addr,  //
          hex_file_data[read_from_address[ADDR_WIDTH-1:2]]  //
      );
      instr_stb <= 0;
    end
  endtask  //automatic

  task automatic data_read;
    input [31:0] read_from_address;
    input [31:0] expected_data;
    output match;
    begin
      @(negedge clk);
      wb_stb  <= 1;
      wb_cyc  <= 1;
      wb_addr <= read_from_address;
      @(posedge clk);
      #(CLK_PERIOD_QUAR);
      match = (wb_rd_data == expected_data);
      $display(  //
          "[%s] Read Data %h from address %h, expected %h",  //
          (match) ? "  OK  " : "FAILED",  //
          wb_rd_data,  //
          wb_addr,  //
          expected_data  //
      );
      wb_stb <= 0;
      wb_cyc <= 0;
    end
  endtask  //automatic

  task automatic data_write;
    input [31:0] write_to_address;
    input [31:0] write_data;
    input [3:0] write_select;
    begin
      @(negedge clk);
      wb_wr_en   <= 1;
      wb_stb     <= 1;
      wb_cyc     <= 1;
      wb_addr    <= write_to_address;
      wb_wr_data <= write_data;
      wb_wr_sel  <= write_select;
      wb_addr    <= write_to_address;
      @(posedge clk);
      #(CLK_PERIOD_QUAR);
      $display("Write Data %h to address %h", wb_wr_data, wb_addr);
      wb_wr_en <= 0;
      wb_stb   <= 0;
      wb_cyc   <= 0;
    end
  endtask  //automatic

  reg [31:0] hex_file_data[0:MEMORY_DEPTH-1];
  initial $readmemh(MEMORY_HEX, hex_file_data);

  task automatic test_instruction_read;
    integer address;
    integer errors = 0;
    integer tests = 0;
    reg match;
    begin
      for (address = 0; address < MEMORY_DEPTH; address = address + 1) begin
        instruction_read(address << 2, match);
        if (!match) errors = errors + 1;
        tests = tests + 1;
      end
      $display(  //
          "\n[%s] Done test_instruction_read with %d\/%d errors",  //
          (errors == 0) ? "  OK  " : "FAILED",  //
          errors,  //
          tests  //
      );
    end
  endtask  //automatic

  task automatic test_data_write_read;
    integer address;
    integer errors = 0;
    integer tests = 0;
    reg [31:0] random_data;
    reg match;
    begin
      for (address = 'h10 << 2; address < MEMORY_DEPTH; address = address + 1) begin
        random_data = $urandom;
        data_write(address, random_data, 4'b1111);
        data_read(address, random_data, match);
        if (!match) errors = errors + 1;
        tests = tests + 1;
      end
      $display(  //
          "\n[%s] Done test_data_write_read with %d\/%d errors",  //
          (errors == 0) ? "  OK  " : "FAILED",  //
          errors,  //
          tests  //
      );
    end
  endtask  //automatic

  initial begin
    test_instruction_read();
    test_data_write_read();

    #(CLK_PERIOD * 10);
    $finish;
  end

  parameter CLK_PERIOD = 10;  // 100 MHz clk
  parameter CLK_PERIOD_HALF = CLK_PERIOD / 2;
  parameter CLK_PERIOD_QUAR = CLK_PERIOD / 4;
  always #(CLK_PERIOD_HALF) clk = !clk;

  reg         clk;

  reg  [31:0] instr_addr;
  wire [31:0] instr;
  reg         instr_stb;
  wire        instr_ack;

  reg         wb_cyc;
  reg         wb_stb;
  reg         wb_wr_en;
  reg  [31:0] wb_addr;
  reg  [31:0] wb_wr_data;
  reg  [ 3:0] wb_wr_sel;
  wire        wb_ack;
  wire        wb_stall;
  wire [31:0] wb_rd_data;

  main_memory #(
      .MEMORY_HEX  (MEMORY_HEX),
      .MEMORY_BYTES(MEMORY_BYTES)
  ) main_memory_inst (
      .clk(clk),

      .instr_addr(instr_addr),
      .instr     (instr),
      .instr_stb (instr_stb),
      .instr_ack (instr_ack),

      .wb_cyc    (wb_cyc),
      .wb_stb    (wb_stb),
      .wb_wr_en  (wb_wr_en),
      .wb_addr   (wb_addr),
      .wb_wr_data(wb_wr_data),
      .wb_wr_sel (wb_wr_sel),
      .wb_ack    (wb_ack),
      .wb_stall  (wb_stall),
      .wb_rd_data(wb_rd_data)
  );
endmodule

vcds/main_memory_tb.vcd
$date
	Tue Jun 25 00:14:56 2024
$end
$version
	Icarus Verilog
$end
$timescale
	1ps
$end
$scope module main_memory_tb $end
$var wire 1 ! wb_stall $end
$var wire 32 " wb_rd_data [31:0] $end
$var wire 1 # wb_ack $end
$var wire 1 $ instr_ack $end
$var wire 32 % instr [31:0] $end
$var parameter 32 & ADDR_WIDTH $end
$var parameter 32 ' CLK_PERIOD $end
$var parameter 32 ( CLK_PERIOD_HALF $end
$var parameter 32 ) CLK_PERIOD_QUAR $end
$var parameter 32 * MEMORY_BYTES $end
$var parameter 32 + MEMORY_DEPTH $end
$var parameter 112 , MEMORY_HEX $end
$var reg 1 - clk $end
$var reg 32 . instr_addr [31:0] $end
$var reg 1 / instr_stb $end
$var reg 32 0 wb_addr [31:0] $end
$var reg 1 1 wb_cyc $end
$var reg 1 2 wb_stb $end
$var reg 32 3 wb_wr_data [31:0] $end
$var reg 1 4 wb_wr_en $end
$var reg 4 5 wb_wr_sel [3:0] $end
$scope module main_memory_inst $end
$var wire 1 - clk $end
$var wire 10 6 instr_addr [9:0] $end
$var wire 1 / instr_stb $end
$var wire 10 7 wb_addr [9:0] $end
$var wire 1 1 wb_cyc $end
$var wire 1 ! wb_stall $end
$var wire 1 2 wb_stb $end
$var wire 32 8 wb_wr_data [31:0] $end
$var wire 1 4 wb_wr_en $end
$var wire 4 9 wb_wr_sel [3:0] $end
$var parameter 32 : ADDR_WIDTH $end
$var parameter 32 ; MEMORY_BYTES $end
$var parameter 32 < MEMORY_DEPTH $end
$var parameter 112 = MEMORY_HEX $end
$var reg 32 > instr [31:0] $end
$var reg 1 $ instr_ack $end
$var reg 1 # wb_ack $end
$var reg 32 ? wb_rd_data [31:0] $end
$scope begin sync_read_process $end
$upscope $end
$scope begin sync_write_process $end
$upscope $end
$upscope $end
$scope task data_read $end
$upscope $end
$scope task data_write $end
$upscope $end
$scope task instruction_read $end
$upscope $end
$scope task test_data_write_read $end
$upscope $end
$scope task test_instruction_read $end
$upscope $end
$upscope $end
$enddefinitions $end
$comment Show the parameter values. $end
$dumpall
b10111000101111011010000110010101111000011100110010111101100001011001000110010000101110011010000110010101111000 =
b100000000 <
b10000000000 ;
b1010 :
b10111000101111011010000110010101111000011100110010111101100001011001000110010000101110011010000110010101111000 ,
b100000000 +
b10000000000 *
b10 )
b101 (
b1010 '
b1010 &
$end
#0
$dumpvars
bx ?
b0 >
b0 9
b0 8
b0 7
b0 6
b0 5
04
b0 3
02
01
b0 0
0/
b0 .
0-
b0 %
0$
0#
bx "
0!
$end
#5000
b110010000000000000010010011 "
b110010000000000000010010011 ?
b110010000000000000010010011 %
b110010000000000000010010011 >
1-
#10000
1/
0-
#15000
1$
1-
#17000
0/
#20000
b100 6
b100 .
1/
0-
#25000
b1001011000000000000100010011 %
b1001011000000000000100010011 >
1-
#27000
0/
#30000
b1000 6
b1000 .
1/
0-
#35000
b1000001000000110110011 %
b1000001000000110110011 >
1-
#37000
0/
#40000
b1100 6
b1100 .
1/
0-
#45000
b11110110101000000000001000010011 %
b11110110101000000000001000010011 >
1-
#47000
0/
#50000
b10000 6
b10000 .
1/
0-
#55000
b100100000001010110011 %
b100100000001010110011 >
1-
#57000
0/
#60000
b10100 6
b10100 .
1/
0-
#65000
b1000100000001100110011 %
b1000100000001100110011 >
1-
#67000
0/
#70000
b11000 6
b11000 .
1/
0-
#75000
b1000001000000000110011 %
b1000001000000000110011 >
1-
#77000
0/
#80000
b11100 6
b11100 .
1/
0-
#85000
b1111101000000000001110010011 %
b1111101000000000001110010011 >
1-
#87000
0/
#90000
b100000 6
b100000 .
1/
0-
#95000
b10000000111000010001100011 %
b10000000111000010001100011 >
1-
#97000
0/
#100000
b100100 6
b100100 .
1/
0-
#105000
b11111100111000000000010000010011 %
b11111100111000000000010000010011 >
1-
#107000
0/
#110000
b101000 6
b101000 .
1/
0-
#115000
b10000001000000000001100011 %
b10000001000000000001100011 >
1-
#117000
0/
#120000
b101100 6
b101100 .
1/
0-
#125000
b10001100111001010001100011 %
b10001100111001010001100011 >
1-
#127000
0/
#130000
b110000 6
b110000 .
1/
0-
#135000
b10010101000001100001100011 %
b10010101000001100001100011 >
1-
#137000
0/
#140000
b110100 6
b110100 .
1/
0-
#145000
b10011000000001110001100011 %
b10011000000001110001100011 >
1-
#147000
0/
#150000
b111000 6
b111000 .
1/
0-
#155000
b100000000000001000001100011 %
b100000000000001000001100011 >
1-
#157000
0/
#160000
b111100 6
b111100 .
1/
0-
#165000
b10100010011 %
b10100010011 >
1-
#167000
0/
#170000
b1000000 6
b1000000 .
1/
0-
#175000
b101110100000000100010010011 %
b101110100000000100010010011 >
1-
#177000
0/
#180000
b1000100 6
b1000100 .
1/
0-
#185000
b100000000000001110011 %
b100000000000001110011 >
1-
#187000
0/
#190000
b1001000 6
b1001000 .
1/
0-
#195000
b100000000010100010011 %
b100000000010100010011 >
1-
#197000
0/
#200000
b1001100 6
b1001100 .
1/
0-
#205000
b101110100000000100010010011 %
b101110100000000100010010011 >
1-
#207000
0/
#210000
b1010000 6
b1010000 .
1/
0-
#215000
b100000000000001110011 %
b100000000000001110011 >
1-
#217000
0/
#220000
b1010100 6
b1010100 .
1/
0-
#225000
b1000000000010100010011 %
b1000000000010100010011 >
1-
#227000
0/
#230000
b1011000 6
b1011000 .
1/
0-
#235000
b101110100000000100010010011 %
b101110100000000100010010011 >
1-
#237000
0/
#240000
b1011100 6
b1011100 .
1/
0-
#245000
b100000000000001110011 %
b100000000000001110011 >
1-
#247000
0/
#250000
b1100000 6
b1100000 .
1/
0-
#255000
b10000000000010100010011 %
b10000000000010100010011 >
1-
#257000
0/
#260000
b1100100 6
b1100100 .
1/
0-
#265000
b101110100000000100010010011 %
b101110100000000100010010011 >
1-
#267000
0/
#270000
b1101000 6
b1101000 .
1/
0-
#275000
b100000000000001110011 %
b100000000000001110011 >
1-
#277000
0/
#280000
b1101100 6
b1101100 .
1/
0-
#285000
b11000000000010100010011 %
b11000000000010100010011 >
1-
#287000
0/
#290000
b1110000 6
b1110000 .
1/
0-
#295000
b101110100000000100010010011 %
b101110100000000100010010011 >
1-
#297000
0/
#300000
b1110100 6
b1110100 .
1/
0-
#305000
b100000000000001110011 %
b100000000000001110011 >
1-
#307000
0/
#310000
b1111000 6
b1111000 .
1/
0-
#315000
b100000000000010100010011 %
b100000000000010100010011 >
1-
#317000
0/
#320000
b1111100 6
b1111100 .
1/
0-
#325000
b101110100000000100010010011 %
b101110100000000100010010011 >
1-
#327000
0/
#330000
b10000000 6
b10000000 .
1/
0-
#335000
b100000000000001110011 %
b100000000000001110011 >
1-
#337000
0/
#340000
b10000100 6
b10000100 .
1/
0-
#345000
b1100101000001 %
b1100101000001 >
1-
#347000
0/
#350000
b10001000 6
b10001000 .
1/
0-
#355000
b1110011011010010111001000000000 %
b1110011011010010111001000000000 >
1-
#357000
0/
#360000
b10001100 6
b10001100 .
1/
0-
#365000
b1000000000111011001100011 %
b1000000000111011001100011 >
1-
#367000
0/
#370000
b10010000 6
b10010000 .
1/
0-
#375000
b1111 %
b1111 >
1-
#377000
0/
#380000
b10010100 6
b10010100 .
1/
0-
#385000
b110011011101100111001000000101 %
b110011011101100111001000000101 >
1-
#387000
0/
#390000
b10011000 6
b10011000 .
1/
0-
#395000
b1110000001100100110100100110010 %
b1110000001100100110100100110010 >
1-
#397000
0/
#400000
b10011100 6
b10011100 .
1/
0-
#405000
b110001 %
b110001 >
1-
#407000
0/
#410000
b10100000 6
b10100000 .
1/
0-
#415000
b0 %
b0 >
1-
#417000
0/
#420000
b10100100 6
b10100100 .
1/
0-
#425000
1-
#427000
0/
#430000
b10101000 6
b10101000 .
1/
0-
#435000
1-
#437000
0/
#440000
b10101100 6
b10101100 .
1/
0-
#445000
1-
#447000
0/
#450000
b10110000 6
b10110000 .
1/
0-
#455000
1-
#457000
0/
#460000
b10110100 6
b10110100 .
1/
0-
#465000
1-
#467000
0/
#470000
b10111000 6
b10111000 .
1/
0-
#475000
1-
#477000
0/
#480000
b10111100 6
b10111100 .
1/
0-
#485000
1-
#487000
0/
#490000
b11000000 6
b11000000 .
1/
0-
#495000
1-
#497000
0/
#500000
b11000100 6
b11000100 .
1/
0-
#505000
1-
#507000
0/
#510000
b11001000 6
b11001000 .
1/
0-
#515000
1-
#517000
0/
#520000
b11001100 6
b11001100 .
1/
0-
#525000
1-
#527000
0/
#530000
b11010000 6
b11010000 .
1/
0-
#535000
1-
#537000
0/
#540000
b11010100 6
b11010100 .
1/
0-
#545000
1-
#547000
0/
#550000
b11011000 6
b11011000 .
1/
0-
#555000
1-
#557000
0/
#560000
b11011100 6
b11011100 .
1/
0-
#565000
1-
#567000
0/
#570000
b11100000 6
b11100000 .
1/
0-
#575000
1-
#577000
0/
#580000
b11100100 6
b11100100 .
1/
0-
#585000
1-
#587000
0/
#590000
b11101000 6
b11101000 .
1/
0-
#595000
1-
#597000
0/
#600000
b11101100 6
b11101100 .
1/
0-
#605000
1-
#607000
0/
#610000
b11110000 6
b11110000 .
1/
0-
#615000
1-
#617000
0/
#620000
b11110100 6
b11110100 .
1/
0-
#625000
1-
#627000
0/
#630000
b11111000 6
b11111000 .
1/
0-
#635000
1-
#637000
0/
#640000
b11111100 6
b11111100 .
1/
0-
#645000
1-
#647000
0/
#650000
b100000000 6
b100000000 .
1/
0-
#655000
1-
#657000
0/
#660000
b100000100 6
b100000100 .
1/
0-
#665000
1-
#667000
0/
#670000
b100001000 6
b100001000 .
1/
0-
#675000
1-
#677000
0/
#680000
b100001100 6
b100001100 .
1/
0-
#685000
1-
#687000
0/
#690000
b100010000 6
b100010000 .
1/
0-
#695000
1-
#697000
0/
#700000
b100010100 6
b100010100 .
1/
0-
#705000
1-
#707000
0/
#710000
b100011000 6
b100011000 .
1/
0-
#715000
1-
#717000
0/
#720000
b100011100 6
b100011100 .
1/
0-
#725000
1-
#727000
0/
#730000
b100100000 6
b100100000 .
1/
0-
#735000
1-
#737000
0/
#740000
b100100100 6
b100100100 .
1/
0-
#745000
1-
#747000
0/
#750000
b100101000 6
b100101000 .
1/
0-
#755000
1-
#757000
0/
#760000
b100101100 6
b100101100 .
1/
0-
#765000
1-
#767000
0/
#770000
b100110000 6
b100110000 .
1/
0-
#775000
1-
#777000
0/
#780000
b100110100 6
b100110100 .
1/
0-
#785000
1-
#787000
0/
#790000
b100111000 6
b100111000 .
1/
0-
#795000
1-
#797000
0/
#800000
b100111100 6
b100111100 .
1/
0-
#805000
1-
#807000
0/
#810000
b101000000 6
b101000000 .
1/
0-
#815000
1-
#817000
0/
#820000
b101000100 6
b101000100 .
1/
0-
#825000
1-
#827000
0/
#830000
b101001000 6
b101001000 .
1/
0-
#835000
1-
#837000
0/
#840000
b101001100 6
b101001100 .
1/
0-
#845000
1-
#847000
0/
#850000
b101010000 6
b101010000 .
1/
0-
#855000
1-
#857000
0/
#860000
b101010100 6
b101010100 .
1/
0-
#865000
1-
#867000
0/
#870000
b101011000 6
b101011000 .
1/
0-
#875000
1-
#877000
0/
#880000
b101011100 6
b101011100 .
1/
0-
#885000
1-
#887000
0/
#890000
b101100000 6
b101100000 .
1/
0-
#895000
1-
#897000
0/
#900000
b101100100 6
b101100100 .
1/
0-
#905000
1-
#907000
0/
#910000
b101101000 6
b101101000 .
1/
0-
#915000
1-
#917000
0/
#920000
b101101100 6
b101101100 .
1/
0-
#925000
1-
#927000
0/
#930000
b101110000 6
b101110000 .
1/
0-
#935000
1-
#937000
0/
#940000
b101110100 6
b101110100 .
1/
0-
#945000
1-
#947000
0/
#950000
b101111000 6
b101111000 .
1/
0-
#955000
1-
#957000
0/
#960000
b101111100 6
b101111100 .
1/
0-
#965000
1-
#967000
0/
#970000
b110000000 6
b110000000 .
1/
0-
#975000
1-
#977000
0/
#980000
b110000100 6
b110000100 .
1/
0-
#985000
1-
#987000
0/
#990000
b110001000 6
b110001000 .
1/
0-
#995000
1-
#997000
0/
#1000000
b110001100 6
b110001100 .
1/
0-
#1005000
1-
#1007000
0/
#1010000
b110010000 6
b110010000 .
1/
0-
#1015000
1-
#1017000
0/
#1020000
b110010100 6
b110010100 .
1/
0-
#1025000
1-
#1027000
0/
#1030000
b110011000 6
b110011000 .
1/
0-
#1035000
1-
#1037000
0/
#1040000
b110011100 6
b110011100 .
1/
0-
#1045000
1-
#1047000
0/
#1050000
b110100000 6
b110100000 .
1/
0-
#1055000
1-
#1057000
0/
#1060000
b110100100 6
b110100100 .
1/
0-
#1065000
1-
#1067000
0/
#1070000
b110101000 6
b110101000 .
1/
0-
#1075000
1-
#1077000
0/
#1080000
b110101100 6
b110101100 .
1/
0-
#1085000
1-
#1087000
0/
#1090000
b110110000 6
b110110000 .
1/
0-
#1095000
1-
#1097000
0/
#1100000
b110110100 6
b110110100 .
1/
0-
#1105000
1-
#1107000
0/
#1110000
b110111000 6
b110111000 .
1/
0-
#1115000
1-
#1117000
0/
#1120000
b110111100 6
b110111100 .
1/
0-
#1125000
1-
#1127000
0/
#1130000
b111000000 6
b111000000 .
1/
0-
#1135000
1-
#1137000
0/
#1140000
b111000100 6
b111000100 .
1/
0-
#1145000
1-
#1147000
0/
#1150000
b111001000 6
b111001000 .
1/
0-
#1155000
1-
#1157000
0/
#1160000
b111001100 6
b111001100 .
1/
0-
#1165000
1-
#1167000
0/
#1170000
b111010000 6
b111010000 .
1/
0-
#1175000
1-
#1177000
0/
#1180000
b111010100 6
b111010100 .
1/
0-
#1185000
1-
#1187000
0/
#1190000
b111011000 6
b111011000 .
1/
0-
#1195000
1-
#1197000
0/
#1200000
b111011100 6
b111011100 .
1/
0-
#1205000
1-
#1207000
0/
#1210000
b111100000 6
b111100000 .
1/
0-
#1215000
1-
#1217000
0/
#1220000
b111100100 6
b111100100 .
1/
0-
#1225000
1-
#1227000
0/
#1230000
b111101000 6
b111101000 .
1/
0-
#1235000
1-
#1237000
0/
#1240000
b111101100 6
b111101100 .
1/
0-
#1245000
1-
#1247000
0/
#1250000
b111110000 6
b111110000 .
1/
0-
#1255000
1-
#1257000
0/
#1260000
b111110100 6
b111110100 .
1/
0-
#1265000
1-
#1267000
0/
#1270000
b111111000 6
b111111000 .
1/
0-
#1275000
1-
#1277000
0/
#1280000
b111111100 6
b111111100 .
1/
0-
#1285000
1-
#1287000
0/
#1290000
b1000000000 6
b1000000000 .
1/
0-
#1295000
1-
#1297000
0/
#1300000
b1000000100 6
b1000000100 .
1/
0-
#1305000
1-
#1307000
0/
#1310000
b1000001000 6
b1000001000 .
1/
0-
#1315000
1-
#1317000
0/
#1320000
b1000001100 6
b1000001100 .
1/
0-
#1325000
1-
#1327000
0/
#1330000
b1000010000 6
b1000010000 .
1/
0-
#1335000
1-
#1337000
0/
#1340000
b1000010100 6
b1000010100 .
1/
0-
#1345000
1-
#1347000
0/
#1350000
b1000011000 6
b1000011000 .
1/
0-
#1355000
1-
#1357000
0/
#1360000
b1000011100 6
b1000011100 .
1/
0-
#1365000
1-
#1367000
0/
#1370000
b1000100000 6
b1000100000 .
1/
0-
#1375000
1-
#1377000
0/
#1380000
b1000100100 6
b1000100100 .
1/
0-
#1385000
1-
#1387000
0/
#1390000
b1000101000 6
b1000101000 .
1/
0-
#1395000
1-
#1397000
0/
#1400000
b1000101100 6
b1000101100 .
1/
0-
#1405000
1-
#1407000
0/
#1410000
b1000110000 6
b1000110000 .
1/
0-
#1415000
1-
#1417000
0/
#1420000
b1000110100 6
b1000110100 .
1/
0-
#1425000
1-
#1427000
0/
#1430000
b1000111000 6
b1000111000 .
1/
0-
#1435000
1-
#1437000
0/
#1440000
b1000111100 6
b1000111100 .
1/
0-
#1445000
1-
#1447000
0/
#1450000
b1001000000 6
b1001000000 .
1/
0-
#1455000
1-
#1457000
0/
#1460000
b1001000100 6
b1001000100 .
1/
0-
#1465000
1-
#1467000
0/
#1470000
b1001001000 6
b1001001000 .
1/
0-
#1475000
1-
#1477000
0/
#1480000
b1001001100 6
b1001001100 .
1/
0-
#1485000
1-
#1487000
0/
#1490000
b1001010000 6
b1001010000 .
1/
0-
#1495000
1-
#1497000
0/
#1500000
b1001010100 6
b1001010100 .
1/
0-
#1505000
1-
#1507000
0/
#1510000
b1001011000 6
b1001011000 .
1/
0-
#1515000
1-
#1517000
0/
#1520000
b1001011100 6
b1001011100 .
1/
0-
#1525000
1-
#1527000
0/
#1530000
b1001100000 6
b1001100000 .
1/
0-
#1535000
1-
#1537000
0/
#1540000
b1001100100 6
b1001100100 .
1/
0-
#1545000
1-
#1547000
0/
#1550000
b1001101000 6
b1001101000 .
1/
0-
#1555000
1-
#1557000
0/
#1560000
b1001101100 6
b1001101100 .
1/
0-
#1565000
1-
#1567000
0/
#1570000
b1001110000 6
b1001110000 .
1/
0-
#1575000
1-
#1577000
0/
#1580000
b1001110100 6
b1001110100 .
1/
0-
#1585000
1-
#1587000
0/
#1590000
b1001111000 6
b1001111000 .
1/
0-
#1595000
1-
#1597000
0/
#1600000
b1001111100 6
b1001111100 .
1/
0-
#1605000
1-
#1607000
0/
#1610000
b1010000000 6
b1010000000 .
1/
0-
#1615000
1-
#1617000
0/
#1620000
b1010000100 6
b1010000100 .
1/
0-
#1625000
1-
#1627000
0/
#1630000
b1010001000 6
b1010001000 .
1/
0-
#1635000
1-
#1637000
0/
#1640000
b1010001100 6
b1010001100 .
1/
0-
#1645000
1-
#1647000
0/
#1650000
b1010010000 6
b1010010000 .
1/
0-
#1655000
1-
#1657000
0/
#1660000
b1010010100 6
b1010010100 .
1/
0-
#1665000
1-
#1667000
0/
#1670000
b1010011000 6
b1010011000 .
1/
0-
#1675000
1-
#1677000
0/
#1680000
b1010011100 6
b1010011100 .
1/
0-
#1685000
1-
#1687000
0/
#1690000
b1010100000 6
b1010100000 .
1/
0-
#1695000
1-
#1697000
0/
#1700000
b1010100100 6
b1010100100 .
1/
0-
#1705000
1-
#1707000
0/
#1710000
b1010101000 6
b1010101000 .
1/
0-
#1715000
1-
#1717000
0/
#1720000
b1010101100 6
b1010101100 .
1/
0-
#1725000
1-
#1727000
0/
#1730000
b1010110000 6
b1010110000 .
1/
0-
#1735000
1-
#1737000
0/
#1740000
b1010110100 6
b1010110100 .
1/
0-
#1745000
1-
#1747000
0/
#1750000
b1010111000 6
b1010111000 .
1/
0-
#1755000
1-
#1757000
0/
#1760000
b1010111100 6
b1010111100 .
1/
0-
#1765000
1-
#1767000
0/
#1770000
b1011000000 6
b1011000000 .
1/
0-
#1775000
1-
#1777000
0/
#1780000
b1011000100 6
b1011000100 .
1/
0-
#1785000
1-
#1787000
0/
#1790000
b1011001000 6
b1011001000 .
1/
0-
#1795000
1-
#1797000
0/
#1800000
b1011001100 6
b1011001100 .
1/
0-
#1805000
1-
#1807000
0/
#1810000
b1011010000 6
b1011010000 .
1/
0-
#1815000
1-
#1817000
0/
#1820000
b1011010100 6
b1011010100 .
1/
0-
#1825000
1-
#1827000
0/
#1830000
b1011011000 6
b1011011000 .
1/
0-
#1835000
1-
#1837000
0/
#1840000
b1011011100 6
b1011011100 .
1/
0-
#1845000
1-
#1847000
0/
#1850000
b1011100000 6
b1011100000 .
1/
0-
#1855000
1-
#1857000
0/
#1860000
b1011100100 6
b1011100100 .
1/
0-
#1865000
1-
#1867000
0/
#1870000
b1011101000 6
b1011101000 .
1/
0-
#1875000
1-
#1877000
0/
#1880000
b1011101100 6
b1011101100 .
1/
0-
#1885000
1-
#1887000
0/
#1890000
b1011110000 6
b1011110000 .
1/
0-
#1895000
1-
#1897000
0/
#1900000
b1011110100 6
b1011110100 .
1/
0-
#1905000
1-
#1907000
0/
#1910000
b1011111000 6
b1011111000 .
1/
0-
#1915000
1-
#1917000
0/
#1920000
b1011111100 6
b1011111100 .
1/
0-
#1925000
1-
#1927000
0/
#1930000
b1100000000 6
b1100000000 .
1/
0-
#1935000
1-
#1937000
0/
#1940000
b1100000100 6
b1100000100 .
1/
0-
#1945000
1-
#1947000
0/
#1950000
b1100001000 6
b1100001000 .
1/
0-
#1955000
1-
#1957000
0/
#1960000
b1100001100 6
b1100001100 .
1/
0-
#1965000
1-
#1967000
0/
#1970000
b1100010000 6
b1100010000 .
1/
0-
#1975000
1-
#1977000
0/
#1980000
b1100010100 6
b1100010100 .
1/
0-
#1985000
1-
#1987000
0/
#1990000
b1100011000 6
b1100011000 .
1/
0-
#1995000
1-
#1997000
0/
#2000000
b1100011100 6
b1100011100 .
1/
0-
#2005000
1-
#2007000
0/
#2010000
b1100100000 6
b1100100000 .
1/
0-
#2015000
1-
#2017000
0/
#2020000
b1100100100 6
b1100100100 .
1/
0-
#2025000
1-
#2027000
0/
#2030000
b1100101000 6
b1100101000 .
1/
0-
#2035000
1-
#2037000
0/
#2040000
b1100101100 6
b1100101100 .
1/
0-
#2045000
1-
#2047000
0/
#2050000
b1100110000 6
b1100110000 .
1/
0-
#2055000
1-
#2057000
0/
#2060000
b1100110100 6
b1100110100 .
1/
0-
#2065000
1-
#2067000
0/
#2070000
b1100111000 6
b1100111000 .
1/
0-
#2075000
1-
#2077000
0/
#2080000
b1100111100 6
b1100111100 .
1/
0-
#2085000
1-
#2087000
0/
#2090000
b1101000000 6
b1101000000 .
1/
0-
#2095000
1-
#2097000
0/
#2100000
b1101000100 6
b1101000100 .
1/
0-
#2105000
1-
#2107000
0/
#2110000
b1101001000 6
b1101001000 .
1/
0-
#2115000
1-
#2117000
0/
#2120000
b1101001100 6
b1101001100 .
1/
0-
#2125000
1-
#2127000
0/
#2130000
b1101010000 6
b1101010000 .
1/
0-
#2135000
1-
#2137000
0/
#2140000
b1101010100 6
b1101010100 .
1/
0-
#2145000
1-
#2147000
0/
#2150000
b1101011000 6
b1101011000 .
1/
0-
#2155000
1-
#2157000
0/
#2160000
b1101011100 6
b1101011100 .
1/
0-
#2165000
1-
#2167000
0/
#2170000
b1101100000 6
b1101100000 .
1/
0-
#2175000
1-
#2177000
0/
#2180000
b1101100100 6
b1101100100 .
1/
0-
#2185000
1-
#2187000
0/
#2190000
b1101101000 6
b1101101000 .
1/
0-
#2195000
1-
#2197000
0/
#2200000
b1101101100 6
b1101101100 .
1/
0-
#2205000
1-
#2207000
0/
#2210000
b1101110000 6
b1101110000 .
1/
0-
#2215000
1-
#2217000
0/
#2220000
b1101110100 6
b1101110100 .
1/
0-
#2225000
1-
#2227000
0/
#2230000
b1101111000 6
b1101111000 .
1/
0-
#2235000
1-
#2237000
0/
#2240000
b1101111100 6
b1101111100 .
1/
0-
#2245000
1-
#2247000
0/
#2250000
b1110000000 6
b1110000000 .
1/
0-
#2255000
1-
#2257000
0/
#2260000
b1110000100 6
b1110000100 .
1/
0-
#2265000
1-
#2267000
0/
#2270000
b1110001000 6
b1110001000 .
1/
0-
#2275000
1-
#2277000
0/
#2280000
b1110001100 6
b1110001100 .
1/
0-
#2285000
1-
#2287000
0/
