src/rtl/regs.sv
`define ZERO_REG_ADDR 0
`define ZERO_REG_DATA 0

module regs (
    input clk,
    input rst,

    // region control by [STAGE 2 DECODE]
    input       rs_rd_en,  // source registers read enable
    input [4:0] rs1,       // source register 1 address
    input [4:0] rs2,       // source register 2 address
    // endregion control by [STAGE 2 DECODE]

    // region control by [STAGE 5 WRITEBACK]
    input [ 4:0] rd,          // destination register address
    input [31:0] rd_wr_data,  // data to be written to destination register
    input        rd_wr_en,    // destination register write enable
    // endregion control by [STAGE 5 WRITEBACK]

    output rs1_rd_data,  // source register 1 value
    output rs2_rd_data   // source register 2 value
);

  reg [31:0] x[1:31];  // regs from x1 to x31 (x0 is hard-wired with 0 value)

  // region read from x
  reg [4:0] r_rs1;  // registered rs1
  reg [4:0] r_rs2;  // registered rs2

  // syn read with clk
  always @(posedge clk, posedge rst) begin : sync_read_process
    if (rst) begin
      r_rs1 <= 0;
      r_rs2 <= 0;
    end else begin
      // only read the register if [STAGE 2 DECODE] is enabled
      if (rs_rd_en) begin
        r_rs1 <= rs1;  // update r_rs1 so the rs1_rdata = x[r_rs1] will also be updated
        r_rs2 <= rs2;  // update r_rs2 so the rs2_rdata = x[r_rs2] will also be updated
      end
    end
  end

  // if read from x0, return 0 else return x[rs]
  assign rs1_rd_data = (r_rs1 == `ZERO_REG_ADDR) ? `ZERO_REG_DATA : x[r_rs1];
  assign rs2_rd_data = (r_rs2 == `ZERO_REG_ADDR) ? `ZERO_REG_DATA : x[r_rs2];
  // endregion read from x

  // region write to x
  // only need to write if not try to write to x0 (zero)
  wire need_write = rd_wr_en && (rd != `ZERO_REG_ADDR);

  // syn write with clk and only write if [Stage 5] (Writeback) is preivously enable.
  integer i;
  always @(posedge clk, posedge rst) begin : sync_write_process
    if (rst) begin
      // reset x
      for (i = 1; i < 32; i = i + 1) begin
        x[i] <= 0;
      end
    end else begin
      // output of [Stage 5 WRITEBACK] is registered so delayed by 1 clk
      if (need_write) x[rd] <= rd_wr_data;
    end
  end
  // endregion write to x
endmodule

src/tb/regs_tb.sv
`timescale 1ns / 1ps
`define VCD_FILE "./vcds/regs_tb.vcd"

module regs_tb ();

  initial begin
    $dumpfile(`VCD_FILE);
    $dumpvars;
  end

  initial begin
    clk = 0;
    rst = 0;
    rs_rd_en = 0;
    rs1 = 0;
    rs2 = 0;
    rd = 0;
    rd_wr_data = 0;
    rd_wr_en = 0;
  end

  initial begin
    rst <= 1;
    #(CLK_PERIOD * 5);
    rst <= 0;
    print_x;
    write_rd(0, 'h1234);
    write_rd(1, 'h9876);
    read_rs(0, 1);
    print_x;

    #(CLK_PERIOD * 10);
    $finish;
  end

  task automatic print_x;
    integer i;
    begin
      for (i = 1; i < 32; i = i + 1) begin
        $display("x[%2d] = %h", i, regs_inst.x[i]);
      end
    end
  endtask  //automatic

  task automatic read_rs;
    input [4:0] rs1_addr;
    input [4:0] rs2_addr;
    reg [31:0] expected_rs1_data;
    reg [31:0] expected_rs2_data;
    reg match_rs1;
    reg match_rs2;
    begin
      @(negedge clk);
      rs_rd_en <= 1;
      rs1      <= rs1_addr;
      rs2      <= rs2_addr;
      @(posedge clk);
      #(CLK_PERIOD_QUAR);
      expected_rs1_data = (rs1_addr == 0) ? 0 : regs_inst.x[rs1_addr];
      match_rs1 = (rs1_rd_data == expected_rs1_data);
      $display(  //
          "[%-6s]Read %08h from rs1 = x[%2d], expected %08h",  //
          match_rs1 ? "OK" : "FAILED",  //
          rs1_rd_data,  //
          rs1_addr,  //
          expected_rs1_data  //
      );
      expected_rs2_data = (rs2_addr == 0) ? 0 : regs_inst.x[rs2_addr];
      match_rs2 = (rs2_rd_data == expected_rs2_data);
      $display(  //
          "[%-6s]Read %08h from rs2 = x[%2d], expected %08h",  //
          match_rs2 ? "OK" : "FAILED",  //
          rs2_rd_data,  //
          rs2_addr,  //
          expected_rs2_data  //
      );
      rs_rd_en <= 0;
    end
  endtask  //automatic

  task automatic write_rd;
    input [4:0] rd_addr;
    input [31:0] rd_write_data;
    begin
      @(negedge clk);
      rd_wr_en   <= 1;
      rd         <= rd_addr;
      rd_wr_data <= rd_write_data;
      @(posedge clk);
      #(CLK_PERIOD_QUAR);
      $display("Write %h to rd = x[%2d]", rd_write_data, rd_addr);
      rd_wr_en <= 0;
    end
  endtask  //automatic


  parameter CLK_PERIOD = 10;  // 100 MHz clk
  parameter CLK_PERIOD_HALF = CLK_PERIOD / 2;
  parameter CLK_PERIOD_QUAR = CLK_PERIOD / 4;
  always #(CLK_PERIOD_HALF) clk = !clk;

  reg         clk;
  reg         rst;

  reg         rs_rd_en;
  reg  [ 4:0] rs1;
  reg  [ 4:0] rs2;

  reg  [ 4:0] rd;
  reg  [31:0] rd_wr_data;
  reg         rd_wr_en;

  wire        rs1_rd_data;
  wire        rs2_rd_data;

  regs regs_inst (
      .clk(clk),
      .rst(rst),

      .rs_rd_en(rs_rd_en),
      .rs1     (rs1),
      .rs2     (rs2),

      .rd        (rd),
      .rd_wr_data(rd_wr_data),
      .rd_wr_en  (rd_wr_en),

      .rs1_rd_data(rs1_rd_data),
      .rs2_rd_data(rs2_rd_data)
  );

endmodule

vcds/regs_tb.vcd
$date
	Tue Jun 25 07:00:05 2024
$end
$version
	Icarus Verilog
$end
$timescale
	1ps
$end
$scope module regs_tb $end
$var wire 1 ! rs2_rd_data $end
$var wire 1 " rs1_rd_data $end
$var parameter 32 # CLK_PERIOD $end
$var parameter 32 $ CLK_PERIOD_HALF $end
$var parameter 32 % CLK_PERIOD_QUAR $end
$var reg 1 & clk $end
$var reg 5 ' rd [4:0] $end
$var reg 32 ( rd_wr_data [31:0] $end
$var reg 1 ) rd_wr_en $end
$var reg 5 * rs1 [4:0] $end
$var reg 5 + rs2 [4:0] $end
$var reg 1 , rs_rd_en $end
$var reg 1 - rst $end
$scope module regs_inst $end
$var wire 1 & clk $end
$var wire 1 . need_write $end
$var wire 5 / rd [4:0] $end
$var wire 32 0 rd_wr_data [31:0] $end
$var wire 1 ) rd_wr_en $end
$var wire 5 1 rs1 [4:0] $end
$var wire 5 2 rs2 [4:0] $end
$var wire 1 , rs_rd_en $end
$var wire 1 - rst $end
$var wire 1 ! rs2_rd_data $end
$var wire 1 " rs1_rd_data $end
$var reg 5 3 r_rs1 [4:0] $end
$var reg 5 4 r_rs2 [4:0] $end
$var integer 32 5 i [31:0] $end
$scope begin sync_read_process $end
$upscope $end
$scope begin sync_write_process $end
$upscope $end
$upscope $end
$scope task print_x $end
$upscope $end
$scope task read_rs $end
$upscope $end
$scope task write_rd $end
$upscope $end
$upscope $end
$enddefinitions $end
$comment Show the parameter values. $end
$dumpall
b10 %
b101 $
b1010 #
$end
#0
$dumpvars
b100000 5
bx 4
bx 3
b0 2
b0 1
b0 0
b0 /
0.
1-
0,
b0 +
b0 *
0)
b0 (
b0 '
0&
x"
x!
$end
#5000
b100000 5
1&
#10000
0&
#15000
b100000 5
1&
#20000
0&
#25000
b100000 5
1&
#30000
0&
#35000
b100000 5
1&
#40000
0&
#45000
b100000 5
1&
#50000
b1001000110100 (
b1001000110100 0
1)
0-
0&
#55000
1&
#57000
0)
#60000
1.
b1001100001110110 (
b1001100001110110 0
b1 '
b1 /
1)
0&
#65000
1&
#67000
0.
0)
#70000
b1 +
b1 2
1,
0&
#75000
0!
0"
b1 4
b0 3
1&
#77000
0,
